foldr2/__init__.py
foldr2/foldr.py
foldr2-0.1.dist-info/DESCRIPTION.rst
foldr2-0.1.dist-info/METADATA
foldr2-0.1.dist-info/RECORD
foldr2-0.1.dist-info/WHEEL
foldr2-0.1.dist-info/metadata.json
foldr2-0.1.dist-info/top_level.txt
