Metadata-Version: 2.0
Name: foldr2
Version: 0.1
Summary: Folds linear things into tree things
Home-page: http://github.com/coreygirard/foldr
Author: Corey Girard
Author-email: corey.r.girard@gmail.com
License: MIT
Platform: UNKNOWN
Classifier: License :: OSI Approved :: MIT License
Classifier: Intended Audience :: Developers
Classifier: Development Status :: 3 - Alpha
